dynamicxml/__init__.py
dynamicxml/dynamicelement.py
dynamicxml/dynamictreebuilder.py
dynamicxml/dynamicxmlparser.py
dynamicxml-1.2.dist-info/LICENSE
dynamicxml-1.2.dist-info/METADATA
dynamicxml-1.2.dist-info/WHEEL
dynamicxml-1.2.dist-info/top_level.txt
dynamicxml-1.2.dist-info/RECORD
