Metadata-Version: 2.1
Name: dynamicxml
Version: 1.2
Summary: An etree utility package
Home-page: https://github.com/claybrooks/dynamic-xml
Author: Clay Brooks
Author-email: clay_brooks@outlook.com
License: UNKNOWN
Platform: UNKNOWN
Classifier: Programming Language :: Python :: 3
Classifier: License :: OSI Approved :: The Unlicense (Unlicense)
Classifier: Operating System :: OS Independent
